part/__init__.py
part/__init__.pyi
part/atomic.py
part/dicts.py
part/py.typed
part/sets.py
part/utils.py
part/values.py
py_part-0.0.6.dist-info/LICENSE
py_part-0.0.6.dist-info/METADATA
py_part-0.0.6.dist-info/WHEEL
py_part-0.0.6.dist-info/top_level.txt
py_part-0.0.6.dist-info/RECORD
