Metadata-Version: 2.1
Name: py-part
Version: 0.0.6
Summary: An interval library package
Home-page: https://github.com/chdemko/py-part
Author: Christophe Demko
Author-email: chdemko@gmail.com
License: BSD-3-Clause
Platform: UNKNOWN
Classifier: Programming Language :: Python :: 3.6
Classifier: Programming Language :: Python :: 3.7
Classifier: Programming Language :: Python :: 3.8
Classifier: Programming Language :: Python :: 3.9
Classifier: License :: OSI Approved :: BSD License
Classifier: Operating System :: OS Independent
Classifier: Development Status :: 3 - Alpha
Classifier: Intended Audience :: Developers
Classifier: Natural Language :: English
Requires-Python: >=3.6
Requires-Dist: sortedcontainers (>=2.3)
Provides-Extra: build
Requires-Dist: setuptools-cythonize (>=1.0) ; extra == 'build'
Provides-Extra: docs
Requires-Dist: sphinx (>=3.5) ; extra == 'docs'
Requires-Dist: sphinx-rtd-theme (>=0.5) ; extra == 'docs'
Requires-Dist: jupyter (>=1.0) ; extra == 'docs'
Requires-Dist: graphviz (>=0.16) ; extra == 'docs'
Requires-Dist: nbsphinx (>=0.8) ; extra == 'docs'
Provides-Extra: test
Requires-Dist: tox (>=3.14) ; extra == 'test'
Requires-Dist: doc8 ; extra == 'test'
Requires-Dist: Pygments (>=2.5) ; extra == 'test'
Requires-Dist: pylint (>=2.5) ; extra == 'test'
Requires-Dist: pep257 ; extra == 'test'
Requires-Dist: mypy ; extra == 'test'
Requires-Dist: black ; extra == 'test'
Requires-Dist: pytest-cov ; extra == 'test'
Requires-Dist: nose2 ; extra == 'test'
